{
  "@microsoft/generator-sharepoint": {
    "plusBeta": false,
    "isCreatingSolution": true,
    "nodeVersion": "16.13.0",
    "sdksVersions": {
      "@microsoft/microsoft-graph-client": "3.0.2",
      "@microsoft/teams-js": "2.9.1"
    },
    "version": "1.17.4",
    "libraryName": "meetings-webpart",
    "libraryId": "d5f840d4-663d-4e99-afac-5547071a31b3",
    "environment": "spo",
    "packageManager": "npm",
    "solutionName": "meetings-webpart",
    "solutionShortDescription": "meetings-webpart description",
    "skipFeatureDeployment": true,
    "isDomainIsolated": false,
    "componentType": "webpart"
  }
}
